<?xml version="1.0" encoding="UTF-8"?>
<keymap version="1" name="Sublime Text" parent="Mac OS X 10.5+">
  <action id="ActivateProjectToolWindow">
    <keyboard-shortcut first-keystroke="meta 1" />
    <keyboard-shortcut first-keystroke="meta K" second-keystroke="meta B" />
  </action>
  <action id="Back">
    <keyboard-shortcut first-keystroke="meta alt LEFT" />
    <mouse-shortcut keystroke="button4" />
  </action>
  <action id="CheckinProject" />
  <action id="Console.TableResult.NavigateAction">
    <keyboard-shortcut first-keystroke="F4" />
  </action>
  <action id="Database.OpenDbStorageAction">
    <keyboard-shortcut first-keystroke="F4" />
  </action>
  <action id="DecrementWindowHeight" />
  <action id="DomCollectionControl.Edit">
    <keyboard-shortcut first-keystroke="F4" />
  </action>
  <action id="DomElementsTreeView.GotoDomElementDeclarationAction">
    <keyboard-shortcut first-keystroke="F4" />
  </action>
  <action id="EditSource">
    <keyboard-shortcut first-keystroke="F4" />
  </action>
  <action id="Editor Paste">
    <keyboard-shortcut first-keystroke="meta V" />
  </action>
  <action id="EditorIndentSelection">
    <keyboard-shortcut first-keystroke="TAB" />
    <keyboard-shortcut first-keystroke="meta CLOSE_BRACKET" />
  </action>
  <action id="EditorPageDown">
    <keyboard-shortcut first-keystroke="PAGE_DOWN" />
    <keyboard-shortcut first-keystroke="meta DOWN" />
  </action>
  <action id="EditorPageDownWithSelection">
    <keyboard-shortcut first-keystroke="shift PAGE_DOWN" />
    <keyboard-shortcut first-keystroke="shift meta DOWN" />
  </action>
  <action id="EditorPageUp">
    <keyboard-shortcut first-keystroke="PAGE_UP" />
    <keyboard-shortcut first-keystroke="meta UP" />
  </action>
  <action id="EditorPageUpWithSelection">
    <keyboard-shortcut first-keystroke="shift PAGE_UP" />
    <keyboard-shortcut first-keystroke="shift meta UP" />
  </action>
  <action id="EditorUnindentSelection">
    <keyboard-shortcut first-keystroke="shift TAB" />
    <keyboard-shortcut first-keystroke="meta OPEN_BRACKET" />
  </action>
  <action id="FileChooser.TogglePathShowing" />
  <action id="Forward">
    <keyboard-shortcut first-keystroke="meta alt RIGHT" />
    <mouse-shortcut keystroke="button5" />
  </action>
  <action id="GotoFile">
    <keyboard-shortcut first-keystroke="meta T" />
  </action>
  <action id="GotoRelated" />
  <action id="GotoTest" />
  <action id="Images.ShowThumbnails" />
  <action id="IncrementWindowHeight" />
  <action id="IncrementalSearch">
    <keyboard-shortcut first-keystroke="meta I" />
  </action>
  <action id="Jdbc.OpenTableEditor">
    <keyboard-shortcut first-keystroke="F4" />
  </action>
  <action id="MoveStatementDown">
    <keyboard-shortcut first-keystroke="control meta DOWN" />
  </action>
  <action id="MoveStatementUp">
    <keyboard-shortcut first-keystroke="control meta UP" />
  </action>
  <action id="ParameterInfo" />
  <action id="PasteMultiple" />
  <action id="RemoteHostView.EditSource">
    <keyboard-shortcut first-keystroke="F4" />
  </action>
  <action id="ReopenClosedTab">
    <keyboard-shortcut first-keystroke="shift meta T" />
  </action>
  <action id="ResizeToolWindowDown" />
  <action id="ResizeToolWindowUp" />
  <action id="SearchEverywhere">
    <keyboard-shortcut first-keystroke="meta P" />
  </action>
  <action id="ShowNavBar">
    <keyboard-shortcut first-keystroke="alt HOME" />
  </action>
  <action id="SwitchApply">
    <keyboard-shortcut first-keystroke="control alt ENTER" />
  </action>
  <action id="SwitchDown">
    <keyboard-shortcut first-keystroke="control alt DOWN" />
  </action>
  <action id="SwitchLeft">
    <keyboard-shortcut first-keystroke="control alt LEFT" />
  </action>
  <action id="SwitchRight">
    <keyboard-shortcut first-keystroke="control alt RIGHT" />
  </action>
  <action id="SwitchUp">
    <keyboard-shortcut first-keystroke="control alt UP" />
  </action>
  <action id="Vcs.UpdateProject" />
</keymap>

